lx_dtypes/__init__.py
lx_dtypes/conftest.py
lx_dtypes/django_settings.py
lx_dtypes/data/README.md
lx_dtypes/data/citations/config.yaml
lx_dtypes/data/citations/sample_references.bib
lx_dtypes/data/citations/data/sample_references.yaml
lx_dtypes/data/information_source_data/config.yaml
lx_dtypes/data/information_source_data/data/unknown.yaml
lx_dtypes/data/logs/.gitignore
lx_dtypes/data/logs/scripts/.gitkeep
lx_dtypes/data/lx_utils/config.yaml
lx_dtypes/data/lx_utils/gender/config.yaml
lx_dtypes/data/lx_utils/gender/default.yaml
lx_dtypes/data/lx_utils/tag/config.yaml
lx_dtypes/data/lx_utils/tag/default.yaml
lx_dtypes/data/lx_utils/unit/config.yaml
lx_dtypes/data/lx_utils/unit/data/concentration.yaml
lx_dtypes/data/lx_utils/unit/data/data.yaml
lx_dtypes/data/lx_utils/unit/data/length.yaml
lx_dtypes/data/lx_utils/unit/data/misc.yaml
lx_dtypes/data/lx_utils/unit/data/rate.yaml
lx_dtypes/data/lx_utils/unit/data/time.yaml
lx_dtypes/data/lx_utils/unit/data/volume.yaml
lx_dtypes/data/lx_utils/unit/data/weight.yaml
lx_dtypes/data/lx_utils/unit_type/config.yaml
lx_dtypes/data/lx_utils/unit_type/data/default.yaml
lx_dtypes/data/sample_knowledge_base/config.yaml
lx_dtypes/data/star_upper_gi/config.yaml
lx_dtypes/data/star_upper_gi/main.yaml
lx_dtypes/data/star_upper_gi/star_u_gi_choices/erefs.yaml
lx_dtypes/data/star_upper_gi/star_u_gi_choices/forrest.yaml
lx_dtypes/data/star_upper_gi/star_u_gi_choices/free_text.yaml
lx_dtypes/data/star_upper_gi/star_u_gi_choices/imaging_modality.yaml
lx_dtypes/data/star_upper_gi/star_u_gi_choices/los_angeles.yaml
lx_dtypes/data/star_upper_gi/star_u_gi_choices/numeric.yaml
lx_dtypes/data/star_upper_gi/star_u_gi_choices/paris.yaml
lx_dtypes/data/star_upper_gi/star_u_gi_choices/prague.yaml
lx_dtypes/data/star_upper_gi/star_u_gi_choices/star_upper_gi_location.yaml
lx_dtypes/data/star_upper_gi/star_u_gi_choices/varices.yaml
lx_dtypes/data/star_upper_gi/star_u_gi_choices/yes_no_unknown.yaml
lx_dtypes-0.1.1.dist-info/METADATA
lx_dtypes-0.1.1.dist-info/WHEEL
lx_dtypes-0.1.1.dist-info/licenses/LICENSE
lx_dtypes-0.1.1.dist-info/RECORD
