Metadata-Version: 2.4
Name: lx-dtypes
Version: 0.1.1
Summary: lx-data-types
Project-URL: Homepage, https://info.coloreg.de
Project-URL: Repository, https://github.com/wg-lux/lx-data-models
Author-email: "Thomas J. Lux" <lux_t1@ukw.de>
Maintainer-email: "Thomas J. Lux" <lux_t1@ukw.de>
License: MIT License
License-File: LICENSE
Keywords: data-models,medical,pydantic,research
Classifier: Development Status :: 3 - Alpha
Classifier: Intended Audience :: Science/Research
Classifier: License :: OSI Approved :: MIT License
Classifier: Programming Language :: Python :: 3.12
Classifier: Topic :: Scientific/Engineering :: Medical Science Apps.
Requires-Python: <3.13,>=3.12
Requires-Dist: bibtexparser>=1.4.0
Requires-Dist: django-ninja>=1.5.1
Requires-Dist: django-stubs-ext>=5.2.8
Requires-Dist: django-stubs[compatible-mypy]>=5.2.8
Requires-Dist: django>=6.0
Requires-Dist: icecream>=2.1.4
Requires-Dist: numpy>=2.2.3
Requires-Dist: opencv-python>=4.12.0.88
Requires-Dist: openpyxl>=3.1.5
Requires-Dist: pandas-stubs>=2.3.3.251201
Requires-Dist: pandas>=2.2.3
Requires-Dist: pandera[io,mypy,pandas]>=0.27.0
Requires-Dist: pillow>=11.3.0
Requires-Dist: pydantic>=2.10.6
Requires-Dist: python-ffmpeg>=2.0.12
Requires-Dist: pyyaml>=6.0.2
Requires-Dist: requests>=2.32.3
Requires-Dist: scikit-learn>=1.8.0
Requires-Dist: scipy>=1.16.1
Requires-Dist: types-pyyaml>=6.0.12.20250915
Provides-Extra: dev
Requires-Dist: build>=1.3.0; extra == 'dev'
Requires-Dist: flake8>=7.3.0; extra == 'dev'
Requires-Dist: furo>=2025.9.25; extra == 'dev'
Requires-Dist: linkify-it-py>=2.0.3; extra == 'dev'
Requires-Dist: mypy>=1.16.0; extra == 'dev'
Requires-Dist: myst-parser>=4.0.1; extra == 'dev'
Requires-Dist: pip>=25.2; extra == 'dev'
Requires-Dist: pre-commit>=4.5.0; extra == 'dev'
Requires-Dist: pytest-cov>=6.1.1; extra == 'dev'
Requires-Dist: pytest-django>=4.11.1; extra == 'dev'
Requires-Dist: pytest-env>=1.1.5; extra == 'dev'
Requires-Dist: pytest-mypy-plugins>=3.2.0; extra == 'dev'
Requires-Dist: pytest-xdist>=3.8.0; extra == 'dev'
Requires-Dist: pytest>=9.0.2; extra == 'dev'
Requires-Dist: ruff>=0.14.8; extra == 'dev'
Requires-Dist: sphinx-autodoc-typehints>=3.5.2; extra == 'dev'
Requires-Dist: sphinx-copybutton>=0.5.2; extra == 'dev'
Requires-Dist: sphinx<9.0,>=8.2.3; extra == 'dev'
Requires-Dist: twine>=6.2.0; extra == 'dev'
Provides-Extra: docs
Requires-Dist: furo>=2025.9.25; extra == 'docs'
Requires-Dist: linkify-it-py>=2.0.3; extra == 'docs'
Requires-Dist: myst-parser>=4.0.1; extra == 'docs'
Requires-Dist: sphinx-autodoc-typehints>=3.5.2; extra == 'docs'
Requires-Dist: sphinx-copybutton>=0.5.2; extra == 'docs'
Requires-Dist: sphinx<9.0,>=8.2.3; extra == 'docs'
